referencer/VERSION
referencer/__init__.py
referencer/__main__.py
referencer/cli.py
referencer/config.py
referencer/document.py
referencer/reference.py
referencer-0.2.3.dist-info/LICENSE.md
referencer-0.2.3.dist-info/METADATA
referencer-0.2.3.dist-info/WHEEL
referencer-0.2.3.dist-info/entry_points.txt
referencer-0.2.3.dist-info/top_level.txt
referencer-0.2.3.dist-info/RECORD
