Metadata-Version: 2.1
Name: referencer
Version: 0.2.3
Summary: Generate a markfown reference from your public API docstrings and add it to your readme
Home-page: https://github.com/roll/referencer-py
Author: Evgeny Karev
Author-email: eskarev@gmail.com
License: MIT
Keywords: docstring,markdown
Platform: UNKNOWN
Classifier: Development Status :: 4 - Beta
Classifier: Intended Audience :: Developers
Classifier: License :: OSI Approved :: MIT License
Classifier: Operating System :: OS Independent
Classifier: Programming Language :: Python :: 3
Classifier: Programming Language :: Python :: 3.6
Classifier: Programming Language :: Python :: 3.7
Classifier: Programming Language :: Python :: 3.8
Classifier: Topic :: Internet :: WWW/HTTP :: Dynamic Content
Classifier: Topic :: Software Development :: Libraries :: Python Modules
Requires-Dist: pydoc-markdown
Requires-Dist: click
Provides-Extra: develop
Requires-Dist: mock ; extra == 'develop'
Requires-Dist: pylama ; extra == 'develop'
Requires-Dist: pytest ; extra == 'develop'
Requires-Dist: pytest-cov ; extra == 'develop'
